oprc_py-0.3.5.dist-info/METADATA
oprc_py-0.3.5.dist-info/WHEEL
oprc_py/__init__.py
oprc_py/oprc_py.cpython-313-powerpc64le-linux-gnu.so
oprc_py/oprc_py.pyi
oprc_py/py.typed
oprc_py-0.3.5.dist-info/RECORD
