Metadata-Version: 2.4
Name: oprc-py
Version: 0.3.5
Classifier: Programming Language :: Rust
Classifier: Programming Language :: Python :: Implementation :: CPython
Classifier: Programming Language :: Python :: Implementation :: PyPy
Requires-Dist: pytest ; extra == 'test'
Requires-Dist: pyright ; extra == 'test'
Requires-Dist: ruff ; extra == 'test'
Provides-Extra: test
Requires-Python: >=3.11
